tgzr/shell_apps/user_workspaces/__init__.py
tgzr/shell_apps/user_workspaces/_version.py
tgzr/shell_apps/user_workspaces/app.py
tgzr/shell_apps/user_workspaces/run_dev.py
tgzr/shell_apps/user_workspaces/run_native.py
tgzr/shell_apps/user_workspaces/settings_models.py
tgzr/shell_apps/user_workspaces/components/__init__.py
tgzr/shell_apps/user_workspaces/components/asset_graph.py
tgzr/shell_apps/user_workspaces/components/page_state.py
tgzr/shell_apps/user_workspaces/components/settings.py
tgzr/shell_apps/user_workspaces/components/utils.py
tgzr/shell_apps/user_workspaces/components/workspace_view.py
tgzr/shell_apps/user_workspaces/pages/__init__.py
tgzr_shell_apps_user_workspaces-0.100.1.dist-info/METADATA
tgzr_shell_apps_user_workspaces-0.100.1.dist-info/WHEEL
tgzr_shell_apps_user_workspaces-0.100.1.dist-info/entry_points.txt
tgzr_shell_apps_user_workspaces-0.100.1.dist-info/licenses/LICENSE
tgzr_shell_apps_user_workspaces-0.100.1.dist-info/RECORD
