Metadata-Version: 2.4
Name: tgzr.shell_apps.user_workspaces
Version: 0.100.1
Summary: A frontend for tgzr.pipeline workspaces.
Project-URL: Documentation, https://github.com/open-tgzr/tgzr.shell_apps.user_workspaces#readme
Project-URL: Issues, https://github.com/open-tgzr/tgzr.shell_apps.user_workspaces/issues
Project-URL: Source, https://github.com/open-tgzr/tgzr.shell_apps.user_workspaces
Author-email: Dee <dee.sometech@gmail.com>
License-Expression: GPL-3.0-or-later
License-File: LICENSE
Classifier: Development Status :: 4 - Beta
Classifier: Programming Language :: Python
Classifier: Programming Language :: Python :: 3.8
Classifier: Programming Language :: Python :: 3.9
Classifier: Programming Language :: Python :: 3.10
Classifier: Programming Language :: Python :: 3.11
Classifier: Programming Language :: Python :: 3.12
Classifier: Programming Language :: Python :: Implementation :: CPython
Classifier: Programming Language :: Python :: Implementation :: PyPy
Requires-Python: >=3.9
Requires-Dist: importlib-metadata
Requires-Dist: tgzr-nice>=0.100
Requires-Dist: tgzr-package-management>=0.100
Requires-Dist: tgzr-pipeline>=0.100
Requires-Dist: tgzr-shell[nicegui]>=0.100
